vintagestory_masterserver/__init__.py
vintagestory_masterserver/admin.py
vintagestory_masterserver/apps.py
vintagestory_masterserver/models.py
vintagestory_masterserver/tests.py
vintagestory_masterserver/urls.py
vintagestory_masterserver/utils.py
vintagestory_masterserver/views.py
vintagestory_masterserver/migrations/0001_initial.py
vintagestory_masterserver/migrations/__init__.py
vintagestory_masterserver-1.0.1.dist-info/LICENCE
vintagestory_masterserver-1.0.1.dist-info/METADATA
vintagestory_masterserver-1.0.1.dist-info/WHEEL
vintagestory_masterserver-1.0.1.dist-info/top_level.txt
vintagestory_masterserver-1.0.1.dist-info/RECORD
