Metadata-Version: 2.2
Name: vintagestory-masterserver
Version: 1.0.1
Summary: A homemade reproduction of the VintageStory Master Server as a Django app.
Author: CDWimmer
License:                     GNU GENERAL PUBLIC LICENSE
Project-URL: Repository, https://github.com/CDWimmer/VintageStoryMasterServer
Classifier: Environment :: Web Environment
Classifier: Programming Language :: Python :: 3.12
Classifier: Programming Language :: Python :: 3.13
Classifier: Topic :: Software Development :: Libraries :: Application Frameworks
Classifier: Topic :: Software Development :: Libraries :: Python Modules
Requires-Python: >=3.12
License-File: LICENCE
Requires-Dist: Django>=5.0
Provides-Extra: dev
Requires-Dist: build==1.2.1; extra == "dev"
Requires-Dist: nox==2024.4.15; extra == "dev"
Requires-Dist: twine==5.1.1; extra == "dev"
